{"title": "théâtre privé : la scène coule-t-elle à paris ?", "newspaper": "NouvelObservateur", "author": ["Jacques Nerson"], "date_publi": "2017-01-01", "theme": "Culture", "content": "Mistinguett proclamerait-elle encore Paris reine du monde ? En tout cas notre capitale règne toujours sur l’industrie du spectacle. Elle compte environ 130 théâtres. Au plus fort de la saison, plus de 500 spectacles, banlieue comprise, y sont chaque jour proposés. Signe de santé ? Pas forcément. Certains, comparant cette prolifération à celle du festival \"off\" d’Avignon, parlent d’une \"avignonisation\" de Paris. De fait, une multitude de salles de moins de cent places ont ouvert ces dernières années. Sans parler des trois Opéras, il y a plusieurs sortes de théâtres à Paris. La Comédie-Française, l’Odéon-Théâtre de l’Europe, le Théâtre national de la Colline, le Théâtre national de Chaillot, sont subventionnés par l’Etat. Le Théâtre de la Ville et les théâtres d’arrondissement, par la ville de Paris. Les autres sont des entreprises privées. Encore que certaines, comme l’Athénée ou le Rond-Point, reçoivent aussi des subventions. Le Syndicat national du Théâtre privé, présidé par Bernard Murat, réunit les principaux. Comment se portent-ils donc ? Les avis divergent. Producteur de spectacles, directeur du Point-Virgule, du Grand Point-Virgule, de Bobino, du Théâtre Antoine (en association avec Laurent Ruquier pour ce dernier lieu), et président des Molières, Jean-Marc Jacques Nerson Journaliste "}