{"title": "Pourquoi l’auteur de l’attaque de Marseille n’a pas été expulsé", "newspaper": "leparisien", "author": "Jean-Michel Décugis et Eric Pelletier (avec Robin Korda)", "date_publi": "02/10/2017", "theme": "Faits divers", "content": " L’homme qui, dimanche après-midi,  (Bouches-du-Rhône), était en situation irrégulière. La veille, il se trouvait encore en garde à vue à Lyon (Rhône), sa reconduite à la frontière étant alors envisagée par la police. Mais cette expulsion n’a pas eu lieu, faute de place dans le centre de rétention administrative, selon une source proche du dossier.\r\n Tout commence vendredi à 18h45 à Lyon, à l’occasion du vol d’une veste bleue d’une valeur de 39 euros au magasin C&A à la Part-Dieu. Interpellé par des agents de sécurité dans les couloirs du centre-commercial, Placé en garde à vue, celui-ci présente , au nom de Ahmed H., 29 ans. Il se dit SDF vivant dans le IIIe arrondissement de Lyon, et par ailleurs consommateur de drogues dures.\r\n Un centre de rétention bondé, un permanent absentParallèlement à l’affaire de vol, finalement classée, une procédure d’expulsion aurait bien été envisagée, la Police aux frontières (PAF) étant même sollicitée pour cela. Le suspect était en effet connu pour sept délits, dont des vols et deux infractions à la législation sur les étrangers en 2005 et 2006. Selon une source proche du dossier, la préfecture du Rhône a indiqué aux services de police que le Centre de rétention administrative (CRA) de Lyon Saint-Exupéry était bondé. Or il s’agit d’ Par ailleurs, et selon plusieurs sources, la person ne de permanence à la préfecture de Lyon, susceptible de signer l'obligation de quitter le territoire (OQTF), était absente ce samedi.\r\nL’homme est finalement remis en liberté samedi vers 15 heures. Le lendemain, il se rend en train à Marseille. A 13h45 précises, sur le parvis de la gare,  A LIRE\r\n> VIDEO. Marseille : le procureur Molins dresse le profil de l'assaillant  "}